covviz/.DS_Store
covviz/__init__.py
covviz/__init__.pyc
covviz/bed.py
covviz/covviz.py
covviz/gff.py
covviz/ped.py
covviz/utils.py
covviz/vcf.py
covviz/__pycache__/__init__.cpython-37.pyc
covviz/__pycache__/bed.cpython-37.pyc
covviz/__pycache__/covviz.cpython-37.pyc
covviz/__pycache__/gff.cpython-37.pyc
covviz/__pycache__/ped.cpython-37.pyc
covviz/__pycache__/utils.cpython-37.pyc
covviz/__pycache__/vcf.cpython-37.pyc
covviz/templates/covviz.html
covviz-1.1.4.dist-info/METADATA
covviz-1.1.4.dist-info/WHEEL
covviz-1.1.4.dist-info/entry_points.txt
covviz-1.1.4.dist-info/top_level.txt
covviz-1.1.4.dist-info/RECORD
