Metadata-Version: 2.1
Name: covviz
Version: 1.1.4
Summary: Multi-sample coverage browser
Home-page: https://github.com/brwnj/covviz
Author: Joe Brown
Author-email: brwnjm@gmail.com
License: UNKNOWN
Platform: UNKNOWN
Classifier: Programming Language :: Python
Classifier: Programming Language :: Python :: 3
Classifier: Programming Language :: Python :: 3.7
Classifier: Programming Language :: Python :: Implementation :: PyPy
Requires-Python: >=3.6.0
Requires-Dist: Jinja2
Requires-Dist: lzstring
Requires-Dist: numpy
Requires-Dist: pandas
